{
  "schemaVersion": 1,
  "status": "ready",
  "generatedAt": "2026-07-20T08:30:00+09:00",
  "generatedBy": "manual-skill",
  "slug": "summer-electricity-saving-2026",
  "statusMessage": "여름 전기요금 절약 카드뉴스가 준비됐어요. 미리보기에서 확인해 주세요.",
  "meta": {
    "category": "생활",
    "topic": "여름철 전기요금 절약 (누진제 완화 + 에너지캐시백)"
  },
  "slides": [
    {
      "id": "cover-1",
      "type": "cover",
      "bodyText": "매년 여름 냉방비 걱정되시죠. 그런데 7~8월엔 누진제 구간 자체가 넓어지고, 에너지캐시백 조건도 완화돼서 미리 알고 준비하면 확실히 아낄 수 있어요.",
      "badge": "daReviewDa",
      "title": "여름 전기요금\n덜 내는 법",
      "subtitle": "누진제 완화 + 캐시백까지\n이번 여름엔 다 챙기세요"
    },
    {
      "id": "quote-1",
      "type": "quote",
      "bodyText": "평소엔 200kWh, 400kWh가 기준이지만 7~8월 두 달만 한시적으로 구간이 넓어져요. 같은 양을 써도 요금이 덜 나오는 거예요.",
      "title": "여름엔 누진제 구간이 넓어져요",
      "highlight": "1단계 300kWh · 2단계 450kWh까지",
      "body": "평소엔 200kWh, 400kWh를 넘으면 다음 구간 요금이 적용되는데, 7~8월 두 달은 이 기준이 각각 300kWh, 450kWh까지 완화돼요. 에어컨을 좀 더 써도 누진 구간을 덜 넘긴다는 뜻이에요."
    },
    {
      "id": "table-1",
      "type": "table",
      "bodyText": "내 사용량이 어느 구간에 있는지 한전ON 앱에서 미리 확인해보는 게 제일 정확해요.",
      "title": "여름철(7~8월) 누진제 구간표",
      "columns": ["구간", "평소 기준", "7~8월 완화 기준"],
      "rows": [
        ["1단계", "~200kWh", "~300kWh"],
        ["2단계", "201~400kWh", "301~450kWh"],
        ["3단계", "401kWh~", "451kWh~"]
      ],
      "note": "완화 구간은 7~8월 사용량에만 한시로 적용돼요."
    },
    {
      "id": "quote-2",
      "type": "quote",
      "bodyText": "작년보다 아주 조금만 아껴도 캐시백을 받을 수 있게 문턱이 낮아졌어요. 신청 안 하면 그냥 넘어가는 돈이라 미리 챙겨두는 게 좋아요.",
      "title": "에너지캐시백, 문턱 낮아졌어요",
      "highlight": "1%만 아껴도 환급 대상",
      "body": "기존엔 작년 같은 달보다 3% 이상 아껴야 캐시백을 받을 수 있었는데, 이번엔 1%만 절감해도 대상이 돼요. 절감률에 따라 최대 1kWh당 120원까지 돌려받을 수 있어요."
    },
    {
      "id": "checklist-1",
      "type": "checklist",
      "bodyText": "체크리스트만 따라가도 전기요금 폭탄은 피할 수 있어요.",
      "title": "여름 전기요금 절약 체크리스트",
      "items": [
        "에어컨 설정 온도 26~27도로 유지하기",
        "한전ON 앱에서 이번 달 예상 사용량 미리 확인하기",
        "에너지캐시백 미리 신청해두기 (작년 동월 대비 1%만 아껴도 대상)",
        "다자녀(3자녀 이상)·대가족(5인 이상)은 30%(월 1.6만원 한도), 장애인(중증)·기초수급자·국가유공자는 정액 감면(평소 월 1.6만원, 7~9월 한시 2만원) 대상인지 확인하기",
        "450kWh 근처면 사용량을 조금만 줄여도 다음 구간을 피할 수 있어요"
      ]
    },
    {
      "id": "outro-1",
      "type": "outro",
      "bodyText": "",
      "title": "시원한 여름 보내세요 🌀",
      "message": "다음엔 여름 휴가철 실손보험 청구 꿀팁으로 찾아올게요.\n도움 되셨다면 이웃추가 해주세요 :)"
    }
  ],
  "body": {
    "postTitle": "여름 전기요금 폭탄 피하는 법, 누진제 완화 + 에너지캐시백 총정리",
    "greeting": "안녕하세요, 다리뷰다입니다.",
    "intro": "요즘 낮에 에어컨 안 틀기 진짜 힘들죠. 그런데 여름엔 누진제 구간이 넓어지고, 캐시백 조건도 완화됐다는 거 알고 계셨나요? 오늘은 이번 여름 전기요금 덜 내는 법을 정리해봤어요.",
    "closing": "다음엔 여름 휴가철 실손보험 청구 꿀팁으로 찾아올게요. 도움 되셨다면 이웃추가 부탁드려요!",
    "disclaimer": "누진제 완화 구간, 캐시백 지급 기준은 한전 지사·시행 시기에 따라 달라질 수 있어요. 신청 전 한전ON 앱이나 한전 고객센터(123)에서 최신 내용을 꼭 확인하세요.",
    "hashtags": "여름전기요금,누진세,에너지캐시백,전기요금절약,한전ON,여름절약꿀팁"
  },
  "sources": [
    { "name": "위기브 - 2026 여름 전기요금 누진제 구간 완화·에어컨 절약법", "url": "https://www.wegive.co.kr/wezine/detail/1928" },
    { "name": "KDI 경제정보센터 - 누진제 개편으로 여름철 전기요금 부담 완화 상시화", "url": "https://eiec.kdi.re.kr/policy/materialView.do?num=190110" },
    { "name": "다음뉴스 - \"450kWh 넘자 전기료 6790원↑\"…여름 누진제 '경계선'", "url": "https://v.daum.net/v/20260713160513612" },
    { "name": "한전 사이버지점 - 전기요금계산기", "url": "https://cyber.kepco.co.kr/ckepco/front/jsp/CY/J/A/CYJAPP000.jsp" },
    { "name": "전기신문 - 한전, 에너지캐시백 확대…1% 절감해도 최대 120원/kWh 지급", "url": "https://www.electimes.com/news/articleView.html?idxno=369659" }
  ],
  "notes": [
    "에너지캐시백 kWh당 환급 단가(최대 120원)와 절감률 구간별 정확한 지급 기준은 지역·시행 시기에 따라 달라질 수 있어, 한전ON 앱 공지로 발행 전 재확인 권장.",
    "복지 할인은 대상별로 방식이 다르다 — 다자녀·대가족·출산가구는 정률(30%, 월 1.6만원 한도), 장애인(중증)·기초수급자·국가유공자는 정액 감면(월 1.6만원, 7~9월 한시 2만원)이다. 최초 배포본에서 이 둘을 뭉뚱그려 '장애인도 30%'인 것처럼 쓴 오류를 2026-07-21 정정함."
  ]
}
